changelog/.gitempty
docs/Makefile
docs/changelog.rst
docs/conf.py
docs/index.rst
docs/make.bat
docs/requirements_table.rst
licenses/LICENSE.rst
licenses/README.rst
solar_wavelength_calibration/__init__.py
solar_wavelength_calibration/atlas/__init__.py
solar_wavelength_calibration/atlas/atlas.py
solar_wavelength_calibration/atlas/base.py
solar_wavelength_calibration/fitter/__init__.py
solar_wavelength_calibration/fitter/parameters.py
solar_wavelength_calibration/fitter/wavelength_fitter.py
solar_wavelength_calibration/tests/__init__.py
solar_wavelength_calibration/tests/conftest.py
solar_wavelength_calibration/tests/test_atlas.py
solar_wavelength_calibration/tests/test_parameters.py
solar_wavelength_calibration/tests/test_wavelength_fitter.py
solar_wavelength_calibration-1.0.1.dist-info/METADATA
solar_wavelength_calibration-1.0.1.dist-info/WHEEL
solar_wavelength_calibration-1.0.1.dist-info/top_level.txt
solar_wavelength_calibration-1.0.1.dist-info/RECORD
