Metadata-Version: 2.4
Name: solar-wavelength-calibration
Version: 1.0.1
Summary: A package for calibrating wavelength data.
Author-email: NSO / AURA <dkistdc@nso.edu>
License: BSD-3-Clause
Project-URL: Homepage, https://nso.edu/dkist/data-center/
Project-URL: Repository, https://bitbucket.org/dkistdc/solar-wavelength-calibration/
Project-URL: Documentation, https://docs.dkist.nso.edu/projects/solar-wavelength-calibration
Project-URL: Help, https://nso.atlassian.net/servicedesk/customer/portal/5
Classifier: Programming Language :: Python
Classifier: Programming Language :: Python :: 3
Classifier: Programming Language :: Python :: 3.11
Requires-Python: >=3.11
Requires-Dist: astropy>=6.1
Requires-Dist: numpy>=1.26.4
Requires-Dist: pooch>=1.8.0
Requires-Dist: pydantic>=2.0
Requires-Dist: scipy>=1.13.0
Requires-Dist: lmfit>=1.3.0
Provides-Extra: test
Requires-Dist: pytest; extra == "test"
Requires-Dist: pytest-cov; extra == "test"
Requires-Dist: pytest-xdist; extra == "test"
Requires-Dist: towncrier; extra == "test"
Requires-Dist: tox>=4; extra == "test"
Requires-Dist: hypothesis; extra == "test"
Provides-Extra: docs
Requires-Dist: sphinx; extra == "docs"
Requires-Dist: sphinx-astropy; extra == "docs"
Requires-Dist: sphinx-changelog; extra == "docs"
Requires-Dist: sphinx-autoapi; extra == "docs"
Requires-Dist: pytest; extra == "docs"
Requires-Dist: towncrier; extra == "docs"
Requires-Dist: dkist-sphinx-theme; extra == "docs"
